{
  "year": "1560",
  "Brazil": [
    "Fort Coligny on Villegagnon Island in Rio de Janeiro is attacked and destroyed during the Portuguese campaign against France Antarctique."
  ],
  "Estonia": [
    "Duke Magnus of Holstein takes power in the Bishopric of &#xD6;sel-Wiek.",
    "Russian troops defeat the Livonian Order in the Battle of H&#xE4;rgm&#xE4;e.",
    "Russian troops capture Central Estonia from the Livonian Order.",
    "Ivan the Terrible decimated the Livonian Order in the Battle of Ergeme."
  ],
  "France": [
    "Francis II died. With no heir, he was succeeded by his brother Charles IX."
  ],
  "Japan": [
    "<i>Battle of Okehazama</i>: Oda Nobunaga emerged victorious."
  ],
  "Malta": [
    "The Knights of Malta escalate their corsairing activities in the western Mediterranean. (to 1565)"
  ],
  "Russia": [
    "<i>Battle of Ergeme</i>: Ivan&apos;s army crushed the forces of the Livonian Order."
  ]
}