{
  "year": "1701",
  "Canada": [
    "The Great Peace of Montreal, between New France and 39 First Nations, is finalized."
  ],
  "England": [
    "The Act of Settlement 1701, which required the English monarch to be Protestant, was passed."
  ],
  "France": [
    "<i>Battle of Carpi</i>: In what was the first battle of the War of the Spanish succession, Austrian invaders encountered the French army at Carpi, and defeated them."
  ],
  "Germany": [
    "Frederick I of Prussia crowned himself king; the Duchy of Prussia became the Kingdom of Prussia."
  ],
  "Philippine": [
    "Domingo Zab&#xE1;lburu de Echevarri appointed Governor-General (1701&#x2013;1709)."
  ],
  "Slovenia": [
    "The Philharmonic Society (<i>Academia philharmonicorum</i>) is established in Ljubljana."
  ],
  "Spain": [
    "<i>War of the Spanish Succession</i>: The war began."
  ]
}