{
  "year": "1513",
  "Poland": [
    "Hortulus Animae, polonice published"
  ],
  "England": [
    "<i>Battle of Flodden Field</i>: Invading England, King James IV of Scotland and thousands of other Scots were killed in a defeat at the hands of the English."
  ],
  "Colombia": [
    "N&#xFA;&#xF1;ez de Balboa discovers the Pacific Ocean"
  ],
  "China": [
    "The Portuguese explorer Jorge &#xC1;lvares arrived on Lintin Island in the Pearl River Delta."
  ],
  "Chile": [
    "Vasco N&#xFA;&#xF1;ez de Balboa becomes the first European to sight the Pacific Ocean from the New World; he calls it Mar del Sur."
  ]
}