{
  "year": "1569",
  "Burma": [
    "Burmese&#x2013;Siamese War (1568&#x2013;69) restores Burmese rule in Siam"
  ],
  "Germany": [
    "Expansion of the Cologne City Hall."
  ],
  "Indinesia": [
    "Peace treaty was signed by Sultan Khairun of Ternate and Governor Lopez De Mesquita of Portuguese."
  ],
  "Latvia": [
    "Lithuania and Poland joined to form the Polish-Lithuanian Commonwealth. Livonia became a joint domain administered directly by both realms."
  ],
  "Poland": [
    "Signing of the Union of Lublin"
  ],
  "Russia": [
    "The Union of Lublin was signed. Poland and the Grand Duchy of Lithuania were merged into the Polish&#x2013;Lithuanian Commonwealth; Poland began aiding Lithuania in its war against Muscovy."
  ]
}