{
  "year": "1824",
  "USA": [
    "The decision in <i>Gibbons v. Ogden</i> affirms federal over state authority in interstate commerce.",
    "<i>U.S. presidential election</i>: An election is held with inconclusive results."
  ],
  "Taiwan": [
    "Immigrants in Taiwan number 1,786,883"
  ],
  "Spain": [
    "<i>Bolivian Independence War</i>: The war ended."
  ],
  "Peru": [
    "<i>Battle of Ayacucho</i>: The Spanish army was defeated, marking the end of Spanish rule in South America."
  ],
  "Malaysia": [
    "The Anglo-Dutch Treaty of 1824 was signed by the United Kingdom and the Netherlands to address issues regarding trade rights in the Spice Islands."
  ],
  "India": [
    "Dayananda Saraswati is born (to 1883)"
  ],
  "Burma": [
    "Start of First Anglo-Burmese War"
  ],
  "Brazil": [
    "Confederation of the Equator rebellion in the Northeast.",
    "The Constitution of 1824 is adopted.",
    "The United States become the first country to recognize the independence of Brazil."
  ],
  "Australia": [
    "A penal colony was founded at Moreton Bay, now the city of Brisbane.",
    "Bathurst and Melville Islands were annexed.",
    "Permission was granted to change the name of the continent from \"New Holland\" to \"Australia\"",
    "The Hume and Hovell expedition travelled overland to Port Phillip Bay and discovered the Murray River (to 1825)"
  ],
  "Armenia": [
    "Founding of Nersessian Academy in Tiflis"
  ]
}